{
  "users": [
    {
      "id": "bnof2ogxj",
      "email": "elia-86tih@mail.ru",
      "pass": "170686",
      "name": "Елена",
      "gender": "female",
      "priv": {
        "showPhase": true,
        "showDay": true,
        "showCareTips": true,
        "showMood": false
      }
    }
  ],
  "curUser": "bnof2ogxj",
  "cycle": {
    "bnof2ogxj": {
      "lps": "2026-06-25",
      "cl": 28,
      "pl": 5
    }
  },
  "logs": {},
  "couples": [],
  "notifs": {},
  "moodForm": {},
  "subs": {},
  "voice": {},
  "_moodSaved": false,
  "_theme": "dark",
  "_fTab": "settings"
}